<?xml version="1.0" encoding="UTF-8" ?>
<!DOCTYPE mapper PUBLIC "-//mybatis.org//DTD Mapper 3.0//EN" "http://mybatis.org/dtd/mybatis-3-mapper.dtd" >
<mapper namespace="com.surpass.mvc.system.sys.dao.SysUserMapper">
	<resultMap id="BaseResultMap" type="com.surpass.mvc.system.sys.model.SysUser">
		<!-- WARNING - @mbggenerated This element is automatically generated by MyBatis Generator, do not modify. This element was generated on Mon 
			Dec 19 14:58:24 CST 2016. -->
		<id column="id" property="id" jdbcType="INTEGER" />
		<result column="sex" property="sex" jdbcType="CHAR" />
		<result column="age" property="age" jdbcType="INTEGER" />
		<result column="tel" property="tel" jdbcType="VARCHAR" />
		<result column="email" property="email" jdbcType="VARCHAR" />
		<result column="bz" property="bz" jdbcType="VARCHAR" />
		<result column="dept_id" property="dept_id" jdbcType="INTEGER" />
		<result column="c_time" property="c_time" jdbcType="TIMESTAMP" />
		<result column="u_time" property="u_time" jdbcType="TIMESTAMP" />
	</resultMap>
	<sql id="Base_Column_List">
		<!-- WARNING - @mbggenerated This element is automatically generated by MyBatis Generator, do not modify. This element was generated on Mon 
			Dec 19 14:58:24 CST 2016. -->
		id, sex, age, tel, email, bz, dept_id, c_time, u_time,emp_id
	</sql>
	<select id="selectByPrimaryKey" resultMap="BaseResultMap" parameterType="java.lang.Integer">
		<!-- WARNING - @mbggenerated This element is automatically generated by MyBatis Generator, do not modify. This element was generated on Mon 
			Dec 19 14:58:24 CST 2016. -->
		select
		<include refid="Base_Column_List" />
		from t_sys_user
		where id = #{id,jdbcType=INTEGER}
	</select>
	<delete id="deleteByPrimaryKey" parameterType="java.lang.Integer">
		<!-- WARNING - @mbggenerated This element is automatically generated by MyBatis Generator, do not modify. This element was generated on Mon 
			Dec 19 14:58:24 CST 2016. -->
		delete from t_sys_user
		where id = #{id,jdbcType=INTEGER}
	</delete>
	<insert id="insert" parameterType="com.surpass.mvc.system.sys.model.SysUser">
		<!-- WARNING - @mbggenerated This element is automatically generated by MyBatis Generator, do not modify. This element was generated on Mon 
			Dec 19 14:58:24 CST 2016. -->
		insert into t_sys_user (id,sex, age, tel,emp_id
		email, bz, dept_id,
		c_time, u_time)
		values (#{id,jdbcType=INTEGER},#{sex,jdbcType=CHAR}
		#{age,jdbcType=INTEGER}, #{tel,jdbcType=VARCHAR},#{emp_id,jdbcType=VARCHAR},
		#{email,jdbcType=VARCHAR}, #{bz,jdbcType=VARCHAR},
		#{dept_id,jdbcType=INTEGER},
		#{c_time,jdbcType=TIMESTAMP}, #{u_time,jdbcType=TIMESTAMP})
	</insert>
	<insert id="insertSelective" useGeneratedKeys="true" keyProperty="id" parameterType="com.surpass.mvc.system.sys.model.SysUser">
		<!-- WARNING - @mbggenerated This element is automatically generated by MyBatis Generator, do not modify. This element was generated on Mon 
			Dec 19 14:58:24 CST 2016. -->
		<selectKey resultType="Integer" order="AFTER" keyProperty="id">
			SELECT LAST_INSERT_ID()
		</selectKey>
		insert into t_sys_user
		<trim prefix="(" suffix=")" suffixOverrides=",">
			<if test="id != null">
				id,
			</if>
			<if test="sex != null">
				sex,
			</if>
			<if test="age != null">
				age,
			</if>
			<if test="tel != null">
				tel,
			</if>
			<if test="email != null">
				email,
			</if>
			<if test="emp_id != null">
				emp_id,
			</if>
			<if test="bz != null">
				bz,
			</if>
			<if test="dept_id != null">
				dept_id,
			</if>
			<if test="c_time != null">
				c_time,
			</if>
			<if test="u_time != null">
				u_time,
			</if>
		</trim>
		<trim prefix="values (" suffix=")" suffixOverrides=",">
			<if test="id != null">
				#{id,jdbcType=INTEGER},
			</if>
			<if test="sex != null">
				#{sex,jdbcType=CHAR},
			</if>
			<if test="age != null">
				#{age,jdbcType=INTEGER},
			</if>
			<if test="tel != null">
				#{tel,jdbcType=VARCHAR},
			</if>
			<if test="email != null">
				#{email,jdbcType=VARCHAR},
			</if>
			<if test="emp_id != null">
				#{emp_id,jdbcType=VARCHAR},
			</if>
			<if test="bz != null">
				#{bz,jdbcType=VARCHAR},
			</if>
			<if test="dept_id != null">
				#{dept_id,jdbcType=INTEGER},
			</if>
			<if test="c_time != null">
				#{c_time,jdbcType=TIMESTAMP},
			</if>
			<if test="u_time != null">
				#{u_time,jdbcType=TIMESTAMP},
			</if>
		</trim>
	</insert>
	<update id="updateByPrimaryKeySelective" parameterType="com.surpass.mvc.system.sys.model.SysUser">
		<!-- WARNING - @mbggenerated This element is automatically generated by MyBatis Generator, do not modify. This element was generated on Mon 
			Dec 19 14:58:24 CST 2016. -->
		update t_sys_user
		<set>
			<if test="sex != null">
				sex = #{sex,jdbcType=CHAR},
			</if>
			<if test="age != null">
				age = #{age,jdbcType=INTEGER},
			</if>
			<if test="tel != null">
				tel = #{tel,jdbcType=VARCHAR},
			</if>
			<if test="emp_id != null">
				emp_id = #{emp_id,jdbcType=VARCHAR},
			</if>
			<if test="email != null">
				email = #{email,jdbcType=VARCHAR},
			</if>
			<if test="bz != null">
				bz = #{bz,jdbcType=VARCHAR},
			</if>
			<if test="dept_id != null">
				dept_id = #{dept_id,jdbcType=INTEGER},
			</if>
			<if test="c_time != null">
				c_time = #{c_time,jdbcType=TIMESTAMP},
			</if>
			<if test="u_time != null">
				u_time = #{u_time,jdbcType=TIMESTAMP},
			</if>
		</set>
		where id = #{id,jdbcType=INTEGER}
	</update>
	<update id="updateByPrimaryKey" parameterType="com.surpass.mvc.system.sys.model.SysUser">
		<!-- WARNING - @mbggenerated This element is automatically generated by MyBatis Generator, do not modify. This element was generated on Mon 
			Dec 19 14:58:24 CST 2016. -->
		update t_sys_user
		set sex = #{sex,jdbcType=CHAR},
		age = #{age,jdbcType=INTEGER},
		tel = #{tel,jdbcType=VARCHAR},
		email =#{email,jdbcType=VARCHAR},
		emp_id =#{emp_id,jdbcType=VARCHAR},
		bz = #{bz,jdbcType=VARCHAR},
		dept_id = #{dept_id,jdbcType=INTEGER},
		c_time =
		#{c_time,jdbcType=TIMESTAMP},
		u_time =
		#{u_time,jdbcType=TIMESTAMP}
		where id = #{id,jdbcType=INTEGER}
	</update>
	<!-- 查询用户信息 -->
	<select id="query" resultType="com.surpass.mvc.system.sys.model.SysUserAccount" parameterType="map">
		select t.* from (select u.*,a.account_id,a.account,a.password,a.username,au.state,au.act_user_id from frm_account_user au left join
		frm_account a on au.account_id=a.account_id left join(select u.*,d.bmmc deptText from t_sys_user u left join t_sys_department d on
		u.dept_id=d.bmbh)u on au.user_id=u.id where au.user_type='1')t
		<where>
			<if test="sysUserAccount.account != null and sysUserAccount.account!='' ">
				and t.account like CONCAT('%','${sysUserAccount.account}','%' )
			</if>
			<if test="sysUserAccount.username != null and sysUserAccount.username!='' ">
				and t.username like CONCAT('%','${sysUserAccount.username}','%' )
			</if>
			<if test="sysUserAccount.deptText != null and sysUserAccount.deptText!='' ">
				and t.dept_id in(select bmbh from t_sys_department where path like CONCAT('${sysUserAccount.deptText}','%' ))
			</if>
		</where>
		<!-- <if test="role.r_name != null and role.r_name!='' "> -->
		<!-- and r.r_name like CONCAT('%','${role.r_name}','%' ) -->
		<!-- </if> -->
		<!-- <if test="role.r_code != null and role.r_code!='' "> -->
		<!-- and r.r_code like CONCAT('%','${role.r_code}','%' ) -->
		<!-- </if> -->
		<!-- <if test="role.state != null and role.state!='' "> -->
		<!-- and r.state = #{role.state} -->
		<!-- </if> -->
		<!-- <if test="role.user_type != null and role.user_type!='' "> -->
		<!-- and r.user_type = #{role.user_type} -->
		<!-- </if> -->
		<!-- <if test="orderBy != null and orderBy !='' "> -->
		<!-- orderBy -->
		<!-- </if> -->
			order by t.c_time
		<![CDATA[
            limit #{start}, #{limit}        
      	]]>
	</select>
	<!-- 查询用户信息数据条数 -->
	<select id="total" resultType="Integer" parameterType="com.surpass.mvc.system.sys.model.SysUserAccount">
		select count(t.id) from (
		select u.id,a.account,a.username,u.dept_id from frm_account_user au left join frm_account a
		on
		au.account_id=a.account_id
		left join
		t_sys_user u on
		au.user_id=u.id where au.user_type='1')t
		<where>
			<if test="account != null and account!='' ">
				and t.account like CONCAT('%','${account}','%' )
			</if>
			<if test="username != null and username!='' ">
				and t.username like CONCAT('%','${username}','%' )
			</if>
			<if test="deptText != null and deptText!='' ">
				and t.dept_id in(select bmbh from t_sys_department where path like CONCAT('${deptText}','%' ))
			</if>
		</where>
		<!-- <if test="r_name != null and r_name!='' "> -->
		<!-- and r_name like CONCAT('%','${r_name}','%' ) -->
		<!-- </if> -->
		<!-- <if test="r_code != null and r_code!='' "> -->
		<!-- and r_code like CONCAT('%','${r_code}','%' ) -->
		<!-- </if> -->
		<!-- <if test="state != null and state!='' "> -->
		<!-- and state = #{state} -->
		<!-- </if> -->
		<!-- <if test="user_type != null and user_type!='' "> -->
		<!-- and user_type = #{user_type} -->
		<!-- </if> -->
	</select>
	<select id="selectSysUserAccountById" resultType="com.surpass.mvc.system.sys.model.SysUserAccount" parameterType="string">
		select t.* from
		(select u.*,a.account_id,a.account,a.password,a.username,au.state,au.act_user_id from frm_account_user au left join frm_account a on
		au.account_id=a.account_id left join(select u.*,d.bmmc deptText from t_sys_user u left join t_sys_department d on u.dept_id=d.bmbh)u on
		au.user_id=u.id where au.user_type='1')t
		where t.act_user_id=#{id}
	</select>
</mapper>